<?xml version="1.0" encoding="UTF-8"?>
<c:signatures xmlns:c="urn:oasis:names:tc:opendocument:xmlns:container"><d:Signature xmlns:d="http://www.w3.org/2000/09/xmldsig#"><d:SignedInfo><d:CanonicalizationMethod Algorithm="http://www.w3.org/TR/2001/REC-xml-c14n-20010315"/><d:SignatureMethod Algorithm="http://www.w3.org/2000/09/xmldsig#hmac-sha1"/><d:Reference URI="mimetype"><d:DigestMethod Algorithm="http://www.w3.org/2000/09/xmldsig#sha1"/><d:DigestValue>jK41hNNg9yHE3Qyjik8tizbadMc=</d:DigestValue></d:Reference><d:Reference URI="META-INF/com.apple.ZipMetadata.plist"><d:DigestMethod Algorithm="http://www.w3.org/2000/09/xmldsig#sha1"/><d:DigestValue>Pnloj21sSOZjvvByuIw6C0XhFno=</d:DigestValue></d:Reference><d:Reference URI="META-INF/com.apple.FixedZipMetadata.bin"><d:DigestMethod Algorithm="http://www.w3.org/2000/09/xmldsig#sha1"/><d:DigestValue>zbXJ+lYrzes584sVg/IkGjIz8ZQ=</d:DigestValue></d:Reference><d:Reference URI="GuidedTour/AboutSwift.xhtml"><d:DigestMethod Algorithm="http://www.w3.org/2000/09/xmldsig#sha1"/><d:DigestValue>IPDpITNd4xJGxLUSLLEvu0vjx1Y=</d:DigestValue></d:Reference><d:Reference URI="GuidedTour/Compatibility.xhtml"><d:DigestMethod Algorithm="http://www.w3.org/2000/09/xmldsig#sha1"/><d:DigestValue>S6uhAqPVITneAKTNYOHsFz5LA2U=</d:DigestValue></d:Reference><d:Reference URI="GuidedTour/GuidedTour.xhtml"><d:DigestMethod Algorithm="http://www.w3.org/2000/09/xmldsig#sha1"/><d:DigestValue>qEqYM8HbSOQ/vgyvH6cxZ0FAgao=</d:DigestValue></d:Reference><d:Reference URI="GuidedTour/GuidedTourPart.xhtml"><d:DigestMethod Algorithm="http://www.w3.org/2000/09/xmldsig#sha1"/><d:DigestValue>rwP9qY4S+Xecfi+jrvawgcDOPLg=</d:DigestValue></d:Reference><d:Reference URI="LanguageGuide/AccessControl.xhtml"><d:DigestMethod Algorithm="http://www.w3.org/2000/09/xmldsig#sha1"/><d:DigestValue>0CoW9au+80Vjh29IhixJX2GK1XU=</d:DigestValue></d:Reference><d:Reference URI="LanguageGuide/AdvancedOperators.xhtml"><d:DigestMethod Algorithm="http://www.w3.org/2000/09/xmldsig#sha1"/><d:DigestValue>PJTWvIzGPY0R8SGSULU1te1ZsHk=</d:DigestValue></d:Reference><d:Reference URI="LanguageGuide/AutomaticReferenceCounting.xhtml"><d:DigestMethod Algorithm="http://www.w3.org/2000/09/xmldsig#sha1"/><d:DigestValue>N7+O6ERc2+e1gtHHXr98LCA1wi0=</d:DigestValue></d:Reference><d:Reference URI="LanguageGuide/BasicOperators.xhtml"><d:DigestMethod Algorithm="http://www.w3.org/2000/09/xmldsig#sha1"/><d:DigestValue>CWF9CtX9M25wgsiUivVSeRxf51Y=</d:DigestValue></d:Reference><d:Reference URI="LanguageGuide/ClassesAndStructures.xhtml"><d:DigestMethod Algorithm="http://www.w3.org/2000/09/xmldsig#sha1"/><d:DigestValue>Mt2Dg6fogjChRBbnaG+CAKAXIgM=</d:DigestValue></d:Reference><d:Reference URI="LanguageGuide/Closures.xhtml"><d:DigestMethod Algorithm="http://www.w3.org/2000/09/xmldsig#sha1"/><d:DigestValue>tM4JOrK4hYcLAQxPx2/qnQruHag=</d:DigestValue></d:Reference><d:Reference URI="LanguageGuide/CollectionTypes.xhtml"><d:DigestMethod Algorithm="http://www.w3.org/2000/09/xmldsig#sha1"/><d:DigestValue>R937EeV7LGtS832kK/pmmH4GSt4=</d:DigestValue></d:Reference><d:Reference URI="LanguageGuide/Concurrency.xhtml"><d:DigestMethod Algorithm="http://www.w3.org/2000/09/xmldsig#sha1"/><d:DigestValue>9+z06UqhaHj8eJQ+d3T8XRRg3jQ=</d:DigestValue></d:Reference><d:Reference URI="LanguageGuide/ControlFlow.xhtml"><d:DigestMethod Algorithm="http://www.w3.org/2000/09/xmldsig#sha1"/><d:DigestValue>nrpQec55lCfRtmKCG2nMu6AUPME=</d:DigestValue></d:Reference><d:Reference URI="LanguageGuide/Deinitialization.xhtml"><d:DigestMethod Algorithm="http://www.w3.org/2000/09/xmldsig#sha1"/><d:DigestValue>0FZDUEdwp1us/k5cNZq+koy04aY=</d:DigestValue></d:Reference><d:Reference URI="LanguageGuide/Enumerations.xhtml"><d:DigestMethod Algorithm="http://www.w3.org/2000/09/xmldsig#sha1"/><d:DigestValue>T9MAgEqqgkSpDTQZzCGGIrekjFE=</d:DigestValue></d:Reference><d:Reference URI="LanguageGuide/ErrorHandling.xhtml"><d:DigestMethod Algorithm="http://www.w3.org/2000/09/xmldsig#sha1"/><d:DigestValue>7YGss9V/QAPqWtWTuYePuKJjexM=</d:DigestValue></d:Reference><d:Reference URI="LanguageGuide/Extensions.xhtml"><d:DigestMethod Algorithm="http://www.w3.org/2000/09/xmldsig#sha1"/><d:DigestValue>Qfi5FbyUtRzMV9maa8vlR9G4UI0=</d:DigestValue></d:Reference><d:Reference URI="LanguageGuide/Functions.xhtml"><d:DigestMethod Algorithm="http://www.w3.org/2000/09/xmldsig#sha1"/><d:DigestValue>693L4/oYQR/7guCTT8r7Lpl9jNI=</d:DigestValue></d:Reference><d:Reference URI="LanguageGuide/Generics.xhtml"><d:DigestMethod Algorithm="http://www.w3.org/2000/09/xmldsig#sha1"/><d:DigestValue>3IBbScFvVHsLWtZ7uD+2spM9yew=</d:DigestValue></d:Reference><d:Reference URI="LanguageGuide/Inheritance.xhtml"><d:DigestMethod Algorithm="http://www.w3.org/2000/09/xmldsig#sha1"/><d:DigestValue>uylu0POJV4G3tB1JqYCm395gDaM=</d:DigestValue></d:Reference><d:Reference URI="LanguageGuide/Initialization.xhtml"><d:DigestMethod Algorithm="http://www.w3.org/2000/09/xmldsig#sha1"/><d:DigestValue>ZTcI/ha9LwYb7gs7D+2tbJN1yPo=</d:DigestValue></d:Reference><d:Reference URI="LanguageGuide/LanguageGuidePart.xhtml"><d:DigestMethod Algorithm="http://www.w3.org/2000/09/xmldsig#sha1"/><d:DigestValue>90vPwObgkHD0tgyAHlGEgg2cn/U=</d:DigestValue></d:Reference><d:Reference URI="LanguageGuide/MemorySafety.xhtml"><d:DigestMethod Algorithm="http://www.w3.org/2000/09/xmldsig#sha1"/><d:DigestValue>4S+3Hn4siMFeSLvF8KCjbz+2G0Q=</d:DigestValue></d:Reference><d:Reference URI="LanguageGuide/Methods.xhtml"><d:DigestMethod Algorithm="http://www.w3.org/2000/09/xmldsig#sha1"/><d:DigestValue>l3NaeR1/0S87AP7He4OB+4qGvaQ=</d:DigestValue></d:Reference><d:Reference URI="LanguageGuide/NestedTypes.xhtml"><d:DigestMethod Algorithm="http://www.w3.org/2000/09/xmldsig#sha1"/><d:DigestValue>gugw2fQ4lKUQVFaFz+COdwSPdm4=</d:DigestValue></d:Reference><d:Reference URI="LanguageGuide/OpaqueTypes.xhtml"><d:DigestMethod Algorithm="http://www.w3.org/2000/09/xmldsig#sha1"/><d:DigestValue>ndi7D6WvifhodGc5hCp1+28yXJ8=</d:DigestValue></d:Reference><d:Reference URI="LanguageGuide/OptionalChaining.xhtml"><d:DigestMethod Algorithm="http://www.w3.org/2000/09/xmldsig#sha1"/><d:DigestValue>ygl/XPqQZXdXJjT6BoNWhUvozP4=</d:DigestValue></d:Reference><d:Reference URI="LanguageGuide/Properties.xhtml"><d:DigestMethod Algorithm="http://www.w3.org/2000/09/xmldsig#sha1"/><d:DigestValue>KGloBS0JtU9V3WadKrPzKVZj434=</d:DigestValue></d:Reference><d:Reference URI="LanguageGuide/Protocols.xhtml"><d:DigestMethod Algorithm="http://www.w3.org/2000/09/xmldsig#sha1"/><d:DigestValue>BfYLP0ixXxAjYWoxOyqdRnAJzuY=</d:DigestValue></d:Reference><d:Reference URI="LanguageGuide/StringsAndCharacters.xhtml"><d:DigestMethod Algorithm="http://www.w3.org/2000/09/xmldsig#sha1"/><d:DigestValue>GxmnWioJJY23tHU8hxnINclnCKI=</d:DigestValue></d:Reference><d:Reference URI="LanguageGuide/Subscripts.xhtml"><d:DigestMethod Algorithm="http://www.w3.org/2000/09/xmldsig#sha1"/><d:DigestValue>c7P4s29LQ2ebUWpaGU9sS6d8jDU=</d:DigestValue></d:Reference><d:Reference URI="LanguageGuide/TheBasics.xhtml"><d:DigestMethod Algorithm="http://www.w3.org/2000/09/xmldsig#sha1"/><d:DigestValue>PxJmz71wJ2nihAxY+/FAXII1thY=</d:DigestValue></d:Reference><d:Reference URI="LanguageGuide/TypeCasting.xhtml"><d:DigestMethod Algorithm="http://www.w3.org/2000/09/xmldsig#sha1"/><d:DigestValue>4uJVg+4Eny3dIznIPK541zOvXqQ=</d:DigestValue></d:Reference><d:Reference URI="META-INF/container.xml"><d:DigestMethod Algorithm="http://www.w3.org/2000/09/xmldsig#sha1"/><d:DigestValue>+D6WA/d4yymCjUJzND9PzJpTbnY=</d:DigestValue></d:Reference><d:Reference URI="ReferenceManual/AboutTheLanguageReference.xhtml"><d:DigestMethod Algorithm="http://www.w3.org/2000/09/xmldsig#sha1"/><d:DigestValue>Wppo792YPMPFrdxm9vbNDyS7j28=</d:DigestValue></d:Reference><d:Reference URI="ReferenceManual/Attributes.xhtml"><d:DigestMethod Algorithm="http://www.w3.org/2000/09/xmldsig#sha1"/><d:DigestValue>1Zo6GvdgEak78rpINfC6AMr3X+s=</d:DigestValue></d:Reference><d:Reference URI="ReferenceManual/Declarations.xhtml"><d:DigestMethod Algorithm="http://www.w3.org/2000/09/xmldsig#sha1"/><d:DigestValue>43Zc2ZsBg8exM9vrEF56DX919M8=</d:DigestValue></d:Reference><d:Reference URI="ReferenceManual/Expressions.xhtml"><d:DigestMethod Algorithm="http://www.w3.org/2000/09/xmldsig#sha1"/><d:DigestValue>RJM/p/v+crUofBvr2mlUQiMllU8=</d:DigestValue></d:Reference><d:Reference URI="ReferenceManual/GenericParametersAndArguments.xhtml"><d:DigestMethod Algorithm="http://www.w3.org/2000/09/xmldsig#sha1"/><d:DigestValue>vQvhfiz+doGKmXT8ZXmTalyBbJ8=</d:DigestValue></d:Reference><d:Reference URI="ReferenceManual/LexicalStructure.xhtml"><d:DigestMethod Algorithm="http://www.w3.org/2000/09/xmldsig#sha1"/><d:DigestValue>fz7V5/peKgyb188UIzOmeyQbFpM=</d:DigestValue></d:Reference><d:Reference URI="ReferenceManual/Patterns.xhtml"><d:DigestMethod Algorithm="http://www.w3.org/2000/09/xmldsig#sha1"/><d:DigestValue>kGqs6evvnnqx4ohvcCIC0aagv28=</d:DigestValue></d:Reference><d:Reference URI="ReferenceManual/ReferenceManualPart.xhtml"><d:DigestMethod Algorithm="http://www.w3.org/2000/09/xmldsig#sha1"/><d:DigestValue>Kwo9OpqbHjYexYfrvfW290zMnt8=</d:DigestValue></d:Reference><d:Reference URI="ReferenceManual/Statements.xhtml"><d:DigestMethod Algorithm="http://www.w3.org/2000/09/xmldsig#sha1"/><d:DigestValue>G1Ha6T8dqtf9Y1P7eQMSoF/k1Vk=</d:DigestValue></d:Reference><d:Reference URI="ReferenceManual/Types.xhtml"><d:DigestMethod Algorithm="http://www.w3.org/2000/09/xmldsig#sha1"/><d:DigestValue>udaOmfE8ZauV3pASFbE5j4rR6ok=</d:DigestValue></d:Reference><d:Reference URI="ReferenceManual/zzSummaryOfTheGrammar.xhtml"><d:DigestMethod Algorithm="http://www.w3.org/2000/09/xmldsig#sha1"/><d:DigestValue>dHbAGwVnZyl6sGLxEciQYzQPNdk=</d:DigestValue></d:Reference><d:Reference URI="RevisionHistory/RevisionHistory.xhtml"><d:DigestMethod Algorithm="http://www.w3.org/2000/09/xmldsig#sha1"/><d:DigestValue>NSw6lASMmfrvpgAr0ISZ9sRs8/0=</d:DigestValue></d:Reference><d:Reference URI="RevisionHistory/RevisionHistoryPart.xhtml"><d:DigestMethod Algorithm="http://www.w3.org/2000/09/xmldsig#sha1"/><d:DigestValue>jIgvfwNmXWlTX/QE824IhVYEeuY=</d:DigestValue></d:Reference><d:Reference URI="Trademarks.xhtml"><d:DigestMethod Algorithm="http://www.w3.org/2000/09/xmldsig#sha1"/><d:DigestValue>F7Nf7u7TdfuTCKseIGrYtUwwYkE=</d:DigestValue></d:Reference><d:Reference URI="_images/CollectionTypes_intro_2x.png"><d:DigestMethod Algorithm="http://www.w3.org/2000/09/xmldsig#sha1"/><d:DigestValue>Ugjpd0xtMbVkzSlblt2VolpMVmU=</d:DigestValue></d:Reference><d:Reference URI="_images/UTF16_2x.png"><d:DigestMethod Algorithm="http://www.w3.org/2000/09/xmldsig#sha1"/><d:DigestValue>/LZAfAXc70z/SZw/zQ8AheXQ+Iw=</d:DigestValue></d:Reference><d:Reference URI="_images/UTF8_2x.png"><d:DigestMethod Algorithm="http://www.w3.org/2000/09/xmldsig#sha1"/><d:DigestValue>+0rQ/rRaYlwkn7DS/vxG6/ESLXM=</d:DigestValue></d:Reference><d:Reference URI="_images/UnicodeScalar_2x.png"><d:DigestMethod Algorithm="http://www.w3.org/2000/09/xmldsig#sha1"/><d:DigestValue>UnIjPYdNy+eeOG/AL388wVzvoYs=</d:DigestValue></d:Reference><d:Reference URI="_images/barcode_QR_2x.png"><d:DigestMethod Algorithm="http://www.w3.org/2000/09/xmldsig#sha1"/><d:DigestValue>Lj8jvSWMOkYKGsTmXxG7JN4Zjvc=</d:DigestValue></d:Reference><d:Reference URI="_images/barcode_UPC_2x.png"><d:DigestMethod Algorithm="http://www.w3.org/2000/09/xmldsig#sha1"/><d:DigestValue>TthOJ2EgVb0FLRX6S8+7ZRebwj8=</d:DigestValue></d:Reference><d:Reference URI="_images/bitshiftSignedAddition_2x.png"><d:DigestMethod Algorithm="http://www.w3.org/2000/09/xmldsig#sha1"/><d:DigestValue>/uHOqtwrct9i+j8MstTyShDdxHI=</d:DigestValue></d:Reference><d:Reference URI="_images/bitshiftSignedFour_2x.png"><d:DigestMethod Algorithm="http://www.w3.org/2000/09/xmldsig#sha1"/><d:DigestValue>ZQZILkuYn9WL2z4D9wVcUY8RB3Y=</d:DigestValue></d:Reference><d:Reference URI="_images/bitshiftSignedMinusFourValue_2x.png"><d:DigestMethod Algorithm="http://www.w3.org/2000/09/xmldsig#sha1"/><d:DigestValue>p0TR/8ltk0PPAexwlqiu76aeONs=</d:DigestValue></d:Reference><d:Reference URI="_images/bitshiftSignedMinusFour_2x.png"><d:DigestMethod Algorithm="http://www.w3.org/2000/09/xmldsig#sha1"/><d:DigestValue>GZteb8wBdAL0TytnkROKqG5PbgM=</d:DigestValue></d:Reference><d:Reference URI="_images/bitshiftSigned_2x.png"><d:DigestMethod Algorithm="http://www.w3.org/2000/09/xmldsig#sha1"/><d:DigestValue>PRP9j9m4qkcnlYm8FqAqsqW3vm4=</d:DigestValue></d:Reference><d:Reference URI="_images/bitshiftUnsigned_2x.png"><d:DigestMethod Algorithm="http://www.w3.org/2000/09/xmldsig#sha1"/><d:DigestValue>lMxoyOk52MidG76VWsycZB143Nw=</d:DigestValue></d:Reference><d:Reference URI="_images/bitwiseAND_2x.png"><d:DigestMethod Algorithm="http://www.w3.org/2000/09/xmldsig#sha1"/><d:DigestValue>6IcPmqGZ92G3lMOaB1oKgQEfOEg=</d:DigestValue></d:Reference><d:Reference URI="_images/bitwiseNOT_2x.png"><d:DigestMethod Algorithm="http://www.w3.org/2000/09/xmldsig#sha1"/><d:DigestValue>6sRrnMl44Ih7ZsIlU05Tcm2y3lM=</d:DigestValue></d:Reference><d:Reference URI="_images/bitwiseOR_2x.png"><d:DigestMethod Algorithm="http://www.w3.org/2000/09/xmldsig#sha1"/><d:DigestValue>c+TlDomQYFZwe0Aq6OxXUrn75RE=</d:DigestValue></d:Reference><d:Reference URI="_images/bitwiseXOR_2x.png"><d:DigestMethod Algorithm="http://www.w3.org/2000/09/xmldsig#sha1"/><d:DigestValue>HdubOb11Fsg3dRmsPEHR+bGx88M=</d:DigestValue></d:Reference><d:Reference URI="_images/chessBoard_2x.png"><d:DigestMethod Algorithm="http://www.w3.org/2000/09/xmldsig#sha1"/><d:DigestValue>7uG2mWuOMgmvdPUWhGLdfiQZwTs=</d:DigestValue></d:Reference><d:Reference URI="_images/closureReferenceCycle01_2x.png"><d:DigestMethod Algorithm="http://www.w3.org/2000/09/xmldsig#sha1"/><d:DigestValue>oz0nip6kcKBrE7hgocPbK23zPv4=</d:DigestValue></d:Reference><d:Reference URI="_images/closureReferenceCycle02_2x.png"><d:DigestMethod Algorithm="http://www.w3.org/2000/09/xmldsig#sha1"/><d:DigestValue>d0t5oJVtbU5TRVJp4F9S2jex9H4=</d:DigestValue></d:Reference><d:Reference URI="_images/computedProperties_2x.png"><d:DigestMethod Algorithm="http://www.w3.org/2000/09/xmldsig#sha1"/><d:DigestValue>0MCPWrEl2yLXbhKepQ4v1VWCRdg=</d:DigestValue></d:Reference><d:Reference URI="_images/coordinateGraphComplex_2x.png"><d:DigestMethod Algorithm="http://www.w3.org/2000/09/xmldsig#sha1"/><d:DigestValue>h7SxyztOD6O6dhdzb4exu3Pu0QU=</d:DigestValue></d:Reference><d:Reference URI="_images/coordinateGraphMedium_2x.png"><d:DigestMethod Algorithm="http://www.w3.org/2000/09/xmldsig#sha1"/><d:DigestValue>jXNhm5tHdgznKJjrzyNWp2cDYDI=</d:DigestValue></d:Reference><d:Reference URI="_images/coordinateGraphSimple_2x.png"><d:DigestMethod Algorithm="http://www.w3.org/2000/09/xmldsig#sha1"/><d:DigestValue>Lvkz/PG0JLPMzsS7CZXB8waa3jA=</d:DigestValue></d:Reference><d:Reference URI="_images/initializerDelegation01_2x.png"><d:DigestMethod Algorithm="http://www.w3.org/2000/09/xmldsig#sha1"/><d:DigestValue>croeMU3zVtHGIbUtYuroCQ22Qi8=</d:DigestValue></d:Reference><d:Reference URI="_images/initializerDelegation02_2x.png"><d:DigestMethod Algorithm="http://www.w3.org/2000/09/xmldsig#sha1"/><d:DigestValue>0ZXLdjWSF5kqDfdx2DUyut7+dhk=</d:DigestValue></d:Reference><d:Reference URI="_images/initializersExample01_2x.png"><d:DigestMethod Algorithm="http://www.w3.org/2000/09/xmldsig#sha1"/><d:DigestValue>gw/R7RdItpMK/BKqmSjTRoH6nUw=</d:DigestValue></d:Reference><d:Reference URI="_images/initializersExample02_2x.png"><d:DigestMethod Algorithm="http://www.w3.org/2000/09/xmldsig#sha1"/><d:DigestValue>tK5pfGrqF/Or6hZIaazYVxK32VE=</d:DigestValue></d:Reference><d:Reference URI="_images/initializersExample03_2x.png"><d:DigestMethod Algorithm="http://www.w3.org/2000/09/xmldsig#sha1"/><d:DigestValue>4Ff6BDFkWuzYNSfFLFortJS75Vk=</d:DigestValue></d:Reference><d:Reference URI="_images/memory_increment_2x.png"><d:DigestMethod Algorithm="http://www.w3.org/2000/09/xmldsig#sha1"/><d:DigestValue>KcJBg4Z+n/t0pv2qKe1YVQbZC8s=</d:DigestValue></d:Reference><d:Reference URI="_images/memory_share_health_maria_2x.png"><d:DigestMethod Algorithm="http://www.w3.org/2000/09/xmldsig#sha1"/><d:DigestValue>OW6nEdGVWN7s/EByea6XR5c9wl8=</d:DigestValue></d:Reference><d:Reference URI="_images/memory_share_health_oscar_2x.png"><d:DigestMethod Algorithm="http://www.w3.org/2000/09/xmldsig#sha1"/><d:DigestValue>xdKhl1OopNhGLj++BAtxhzVWux4=</d:DigestValue></d:Reference><d:Reference URI="_images/memory_shopping_2x.png"><d:DigestMethod Algorithm="http://www.w3.org/2000/09/xmldsig#sha1"/><d:DigestValue>2tPAls2pI1VgcgxFTZrRp5yrx3o=</d:DigestValue></d:Reference><d:Reference URI="_images/multilineStringWhitespace_2x.png"><d:DigestMethod Algorithm="http://www.w3.org/2000/09/xmldsig#sha1"/><d:DigestValue>pqN2JjzE2PNK/WmRjxvpSSIv67E=</d:DigestValue></d:Reference><d:Reference URI="_images/overflowAddition_2x.png"><d:DigestMethod Algorithm="http://www.w3.org/2000/09/xmldsig#sha1"/><d:DigestValue>TQYaymctCBGCV0B5F9UnJavfNZE=</d:DigestValue></d:Reference><d:Reference URI="_images/overflowSignedSubtraction_2x.png"><d:DigestMethod Algorithm="http://www.w3.org/2000/09/xmldsig#sha1"/><d:DigestValue>ET+HwsYXYk2ACB9x3/thIi0c+5s=</d:DigestValue></d:Reference><d:Reference URI="_images/overflowUnsignedSubtraction_2x.png"><d:DigestMethod Algorithm="http://www.w3.org/2000/09/xmldsig#sha1"/><d:DigestValue>jqV0iPi28NW7i1w5CAJUiJh9AqM=</d:DigestValue></d:Reference><d:Reference URI="_images/referenceCycle01_2x.png"><d:DigestMethod Algorithm="http://www.w3.org/2000/09/xmldsig#sha1"/><d:DigestValue>RFGrTXyf8AoBqdu1BO0Ydsgrblo=</d:DigestValue></d:Reference><d:Reference URI="_images/referenceCycle02_2x.png"><d:DigestMethod Algorithm="http://www.w3.org/2000/09/xmldsig#sha1"/><d:DigestValue>oo8NHn9b0V9lwSXRhwCtg56JHhI=</d:DigestValue></d:Reference><d:Reference URI="_images/referenceCycle03_2x.png"><d:DigestMethod Algorithm="http://www.w3.org/2000/09/xmldsig#sha1"/><d:DigestValue>lrA+0nZfjN8ixVa9DJViGXo/DDg=</d:DigestValue></d:Reference><d:Reference URI="_images/remainderInteger_2x.png"><d:DigestMethod Algorithm="http://www.w3.org/2000/09/xmldsig#sha1"/><d:DigestValue>pfGZD5V22gu6pgXq8PcasBsa28o=</d:DigestValue></d:Reference><d:Reference URI="_images/setEulerDiagram_2x.png"><d:DigestMethod Algorithm="http://www.w3.org/2000/09/xmldsig#sha1"/><d:DigestValue>zFllJ6pYe4gInMtATHg1pzJkX0A=</d:DigestValue></d:Reference><d:Reference URI="_images/setVennDiagram_2x.png"><d:DigestMethod Algorithm="http://www.w3.org/2000/09/xmldsig#sha1"/><d:DigestValue>7Xstna6ieZcYSv0eiRXdMdWXVDE=</d:DigestValue></d:Reference><d:Reference URI="_images/sharedStateClass_2x.png"><d:DigestMethod Algorithm="http://www.w3.org/2000/09/xmldsig#sha1"/><d:DigestValue>V1Qn/chi40IxupV/Zjc48rCrnOg=</d:DigestValue></d:Reference><d:Reference URI="_images/sharedStateStruct_2x.png"><d:DigestMethod Algorithm="http://www.w3.org/2000/09/xmldsig#sha1"/><d:DigestValue>mEuq/d8BirZb2d/T9gVvN3PAe6U=</d:DigestValue></d:Reference><d:Reference URI="_images/snakesAndLadders_2x.png"><d:DigestMethod Algorithm="http://www.w3.org/2000/09/xmldsig#sha1"/><d:DigestValue>0N04w+Geu06r2Iv0jXxXsI92CuU=</d:DigestValue></d:Reference><d:Reference URI="_images/stackPoppedOneString_2x.png"><d:DigestMethod Algorithm="http://www.w3.org/2000/09/xmldsig#sha1"/><d:DigestValue>gh38ABnrXQSOdx1Oz9qcVMWw9gI=</d:DigestValue></d:Reference><d:Reference URI="_images/stackPushPop_2x.png"><d:DigestMethod Algorithm="http://www.w3.org/2000/09/xmldsig#sha1"/><d:DigestValue>Fd/dF2WNFqUxYKsmkpZeGEs8e68=</d:DigestValue></d:Reference><d:Reference URI="_images/stackPushedFourStrings_2x.png"><d:DigestMethod Algorithm="http://www.w3.org/2000/09/xmldsig#sha1"/><d:DigestValue>Y28Zld/RAD6iF1UuWSxsZOtIYPo=</d:DigestValue></d:Reference><d:Reference URI="_images/staticPropertiesVUMeter_2x.png"><d:DigestMethod Algorithm="http://www.w3.org/2000/09/xmldsig#sha1"/><d:DigestValue>pMd1rVzNDp64rtnfURxeoIC9OiY=</d:DigestValue></d:Reference><d:Reference URI="_images/stringSubstring_2x.png"><d:DigestMethod Algorithm="http://www.w3.org/2000/09/xmldsig#sha1"/><d:DigestValue>9yirQYwCW+FgU05DYRW8m01kWGs=</d:DigestValue></d:Reference><d:Reference URI="_images/subscriptMatrix01_2x.png"><d:DigestMethod Algorithm="http://www.w3.org/2000/09/xmldsig#sha1"/><d:DigestValue>elxlHZQU6ioTIzQEFrctIA6EKyk=</d:DigestValue></d:Reference><d:Reference URI="_images/subscriptMatrix02_2x.png"><d:DigestMethod Algorithm="http://www.w3.org/2000/09/xmldsig#sha1"/><d:DigestValue>Zo5Cs05G6ZdC8bwRUZtlEJFmJIY=</d:DigestValue></d:Reference><d:Reference URI="_images/twoPhaseInitialization01_2x.png"><d:DigestMethod Algorithm="http://www.w3.org/2000/09/xmldsig#sha1"/><d:DigestValue>8JSwUbo8bigB7aTy1by2o10h79s=</d:DigestValue></d:Reference><d:Reference URI="_images/twoPhaseInitialization02_2x.png"><d:DigestMethod Algorithm="http://www.w3.org/2000/09/xmldsig#sha1"/><d:DigestValue>sSZ4foQF17TYTTu2kHy5fU63Ltw=</d:DigestValue></d:Reference><d:Reference URI="_images/unownedOptionalReference_2x.png"><d:DigestMethod Algorithm="http://www.w3.org/2000/09/xmldsig#sha1"/><d:DigestValue>xsAnAGLln4WYS27KifdV+7Q10fA=</d:DigestValue></d:Reference><d:Reference URI="_images/unownedReference01_2x.png"><d:DigestMethod Algorithm="http://www.w3.org/2000/09/xmldsig#sha1"/><d:DigestValue>3nx/Pars85KThg9kdhXP98SV5RY=</d:DigestValue></d:Reference><d:Reference URI="_images/unownedReference02_2x.png"><d:DigestMethod Algorithm="http://www.w3.org/2000/09/xmldsig#sha1"/><d:DigestValue>RIMffE6q6QTtOE6MBZDjVMLINBA=</d:DigestValue></d:Reference><d:Reference URI="_images/vectorAddition_2x.png"><d:DigestMethod Algorithm="http://www.w3.org/2000/09/xmldsig#sha1"/><d:DigestValue>6RZthRtEQ0xiygnwK5rb6crV/AI=</d:DigestValue></d:Reference><d:Reference URI="_images/weakReference01_2x.png"><d:DigestMethod Algorithm="http://www.w3.org/2000/09/xmldsig#sha1"/><d:DigestValue>zZevh+yL1GDaPe6HmG3qUz14YsM=</d:DigestValue></d:Reference><d:Reference URI="_images/weakReference02_2x.png"><d:DigestMethod Algorithm="http://www.w3.org/2000/09/xmldsig#sha1"/><d:DigestValue>UEqBNlDA1zJ/Iz1XZoqgE5KCr1I=</d:DigestValue></d:Reference><d:Reference URI="_images/weakReference03_2x.png"><d:DigestMethod Algorithm="http://www.w3.org/2000/09/xmldsig#sha1"/><d:DigestValue>VjPrnnmqlAUs8jgSXfqTMVVU5IQ=</d:DigestValue></d:Reference><d:Reference URI="_static/basic.css"><d:DigestMethod Algorithm="http://www.w3.org/2000/09/xmldsig#sha1"/><d:DigestValue>vThF2gYCpVqxYwp64i+N4f8AdJ0=</d:DigestValue></d:Reference><d:Reference URI="_static/cover.jpg"><d:DigestMethod Algorithm="http://www.w3.org/2000/09/xmldsig#sha1"/><d:DigestValue>I6diPU6RvrzjM9GHyIfbfR0lOvs=</d:DigestValue></d:Reference><d:Reference URI="_static/epub.css"><d:DigestMethod Algorithm="http://www.w3.org/2000/09/xmldsig#sha1"/><d:DigestValue>tJRd/mS09YPfolFZUrCXbX4M1nU=</d:DigestValue></d:Reference><d:Reference URI="_static/file.png"><d:DigestMethod Algorithm="http://www.w3.org/2000/09/xmldsig#sha1"/><d:DigestValue>Uf0uTskk6CLF1DT6mMz8cMMDgPU=</d:DigestValue></d:Reference><d:Reference URI="_static/minus.png"><d:DigestMethod Algorithm="http://www.w3.org/2000/09/xmldsig#sha1"/><d:DigestValue>ifQXjx+RetA3JvMH/m0uKNahcGo=</d:DigestValue></d:Reference><d:Reference URI="_static/plus.png"><d:DigestMethod Algorithm="http://www.w3.org/2000/09/xmldsig#sha1"/><d:DigestValue>Nlq+Y94GPvLZfTyqzENRJBW1qDU=</d:DigestValue></d:Reference><d:Reference URI="_static/pygments.css"><d:DigestMethod Algorithm="http://www.w3.org/2000/09/xmldsig#sha1"/><d:DigestValue>UQwyJ6mb190XxekQGuqA60ceRMI=</d:DigestValue></d:Reference><d:Reference URI="content.opf"><d:DigestMethod Algorithm="http://www.w3.org/2000/09/xmldsig#sha1"/><d:DigestValue>OQOa7KYmneG7vjOXOxRdlJ0/wKE=</d:DigestValue></d:Reference><d:Reference URI="nav.xhtml"><d:DigestMethod Algorithm="http://www.w3.org/2000/09/xmldsig#sha1"/><d:DigestValue>U+E9vWBKtFZm1oxP3FEOtIKdlEg=</d:DigestValue></d:Reference><d:Reference URI="toc.ncx"><d:DigestMethod Algorithm="http://www.w3.org/2000/09/xmldsig#sha1"/><d:DigestValue>rnZb8jUPZZt0CVxGUue6JP6NPEg=</d:DigestValue></d:Reference></d:SignedInfo><d:SignatureValue>LGlxptuBkOkBc6FYoFcA9vMxFRY=</d:SignatureValue><d:KeyInfo><d:KeyName>1</d:KeyName></d:KeyInfo></d:Signature></c:signatures>
